tgol/__init__.py
tgol/__main__.py
tgol/cli.py
tgol/grid.py
tgol/patterns.py
tgol/patterns.toml
tgol/views.py
tgol-1.0.0.dist-info/entry_points.txt
tgol-1.0.0.dist-info/WHEEL
tgol-1.0.0.dist-info/METADATA
tgol-1.0.0.dist-info/RECORD
