Metadata-Version: 2.1
Name: tgol
Version: 1.0.0
Summary: Conway's Game of Life in terminal
Author-email: Ahmed Bin Nasser <munnaa329@gmail.com>
Requires-Dist: tomli; python_version < "3.11"
